{
  "AnchorList": [],
  "AreaAnchorName": "LevelArea_P80504_F80504001_G40",
  "AudienceList": [],
  "BattleAreaList": [],
  "Category": "Custom",
  "ConflictIDList": [],
  "ConflictWhiteList": [],
  "CrowdList": [],
  "CurveList": [],
  "DistrictList": [],
  "GroupName": "RogueModule_Magic_Area",
  "IsHoyoGroup": true,
  "LittleGameList": [],
  "LoadSide": "Server",
  "MonsterList": [],
  "NPCList": [],
  "PathwayList": [],
  "PedestrianList": [],
  "PedestrianV2List": [],
  "PropList": [
    {
      "BridgeStateRotations": [],
      "CameraCenterEntityList": [],
      "CameraConfig": {},
      "CampID": 4,
      "CustomTriggerMap": {},
      "CustomTriggerMapV2": {},
      "DialogueGroups": [],
      "DialogueTriggerAngle": 120,
      "DialogueTriggerSkipFakeAvatar": true,
      "DialogueTriggerSkipSpecifiedFakeAvatarList": [],
      "ID": 300001,
      "InteractTitle": {
        "Hash": 371857150
      },
      "LoadOnInitial": true,
      "LookAtPlayerTriggerRadius": 2,
      "Name": "Prop1",
      "OverrideHintRange": -1,
      "OverrideLockRaycastOffset": 1.5,
      "OverrideMapIconType": -1,
      "OverridePropName": {
        "Hash": 371857150
      },
      "OverrideSoundRange": -1,
      "PosX": -65.02,
      "PosY": 52.822,
      "PosZ": 102.96,
      "PropID": 1030,
      "RotY": 77.36787,
      "Scale": {
        "magnitude": 2.22589684,
        "normalized": {
          "magnitude": 1,
          "sqrMagnitude": 1.00000012,
          "x": 0.772228062,
          "y": 0.4492571,
          "z": 0.4492571
        },
        "sqrMagnitude": 4.954617,
        "x": 1.7189,
        "y": 1,
        "z": 1
      },
      "ServerInteractVerificationIDList": [],
      "SpawnConfig": {
        "EntitySpawnConfig": {
          "BlackInDistance": 25,
          "NeedBlackIn": true,
          "NeedFadeIn": true,
          "NeedFadeOut": true
        }
      },
      "StateConfigs": [],
      "TagOverrideComponents": {},
      "TalkDialogGroupIDList": [],
      "ValueSource": {}
    },
    {
      "BridgeStateRotations": [],
      "CameraCenterEntityList": [],
      "CameraConfig": {},
      "CampID": 4,
      "CustomTriggerMap": {},
      "CustomTriggerMapV2": {},
      "DialogueGroups": [],
      "DialogueTriggerAngle": 120,
      "DialogueTriggerSkipFakeAvatar": true,
      "DialogueTriggerSkipSpecifiedFakeAvatarList": [],
      "ID": 300002,
      "InteractTitle": {
        "Hash": 371857150
      },
      "LoadOnInitial": true,
      "LookAtPlayerTriggerRadius": 2,
      "Name": "Prop2",
      "OverrideHintRange": -1,
      "OverrideLockRaycastOffset": 1.5,
      "OverrideMapIconType": -1,
      "OverridePropName": {
        "Hash": 371857150
      },
      "OverrideSoundRange": -1,
      "PosX": -42.85,
      "PosY": 54.0509,
      "PosZ": 130.82,
      "PropID": 1030,
      "RotY": 167.0468,
      "Scale": {
        "magnitude": 1.73176789,
        "normalized": {
          "magnitude": 1,
          "sqrMagnitude": 1,
          "x": 0.5771616,
          "y": 0.5774446,
          "z": 0.5774446
        },
        "sqrMagnitude": 2.99902,
        "x": 0.99951,
        "y": 1,
        "z": 1
      },
      "ServerInteractVerificationIDList": [],
      "SpawnConfig": {
        "EntitySpawnConfig": {
          "BlackInDistance": 25,
          "NeedBlackIn": true,
          "NeedFadeIn": true,
          "NeedFadeOut": true
        }
      },
      "StateConfigs": [],
      "TagOverrideComponents": {},
      "TalkDialogGroupIDList": [],
      "ValueSource": {}
    }
  ],
  "SaveType": "Permanent",
  "SmartObjectList": [],
  "StreamingTemplateType": "Standard",
  "ValueSource": {},
  "WaypointList": []
}